[{"line":1,"elements":[{"start_timestamp":"2023-02-22T20:11:24.191Z","line":3,"name":"Login User with correct email and password","description":"","id":"testcase02;login-user-with-correct-email-and-password","type":"scenario","keyword":"Scenario","steps":[{"result":{"duration":6664500600,"status":"passed"},"line":4,"name":"Tevfik Navigate to url","match":{"location":"stepDefinitions.StepDefinitionsTestCase02.tevfik_navigate_to_url()"},"keyword":"Given "},{"result":{"duration":11291800,"status":"passed"},"line":5,"name":"Tevfik Verify that home page is visible successfully","match":{"location":"stepDefinitions.StepDefinitionsTestCase02.tevfik_verify_that_home_page_is_visible_successfully()"},"keyword":"When "}],"tags":[{"name":"@Tevfik"}]}],"name":"TestCase02","description":"","id":"testcase02","keyword":"Feature","uri":"file:src/test/resources/features/TestCase02.feature","tags":[]}]